[
  {
    "id": 1001,
    "need_time": 300,
    "reward_list": [
      {
        "type": 1,
        "reward_value": 1000
      }
    ]
  },
  {
    "id": 1002,
    "need_time": 600,
    "reward_list": [
      {
        "type": 3,
        "reward_value": 5
      }
    ]
  },
  {
    "id": 1003,
    "need_time": 900,
    "reward_list": [
      {
        "type": 4,
        "reward_value": 5
      }
    ]
  },
  {
    "id": 1004,
    "need_time": 1200,
    "reward_list": [
      {
        "type": 5,
        "reward_value": 5
      }
    ]
  },
  {
    "id": 1005,
    "need_time": 1800,
    "reward_list": [
      {
        "type": 1,
        "reward_value": 2000
      }
    ]
  },
  {
    "id": 1006,
    "need_time": 2100,
    "reward_list": [
      {
        "type": 12,
        "reward_value": 10
      }
    ]
  },
  {
    "id": 1007,
    "need_time": 2700,
    "reward_list": [
      {
        "type": 12,
        "reward_value": 20
      }
    ]
  },
  {
    "id": 1008,
    "need_time": 3000,
    "reward_list": [
      {
        "type": 12,
        "reward_value": 20
      }
    ]
  },
  {
    "id": 1009,
    "need_time": 3600,
    "reward_list": [
      {
        "type": 12,
        "reward_value": 50
      }
    ]
  }
]